{
  "gitSyncId": "673f672562b6fd1870633c84_9ff2e525-1a1b-4720-b7e5-3c27627ffda5",
  "id": "Quản lý đơn yêu cầu cứu trợ_Api2",
  "pluginId": "restapi-plugin",
  "pluginType": "API",
  "unpublishedAction": {
    "actionConfiguration": {
      "autoGeneratedHeaders": [],
      "body": "",
      "bodyFormData": [],
      "encodeParamsToggle": true,
      "formData": {
        "apiContentType": "none"
      },
      "headers": [
        {
          "key": "",
          "value": ""
        },
        {
          "key": "",
          "value": ""
        }
      ],
      "httpMethod": "GET",
      "httpVersion": "HTTP11",
      "paginationType": "NONE",
      "pluginSpecifiedTemplates": [
        {
          "value": true
        }
      ],
      "queryParameters": [
        {
          "key": "",
          "value": ""
        },
        {
          "key": "",
          "value": ""
        }
      ],
      "timeoutInMillisecond": 10000
    },
    "confirmBeforeExecute": false,
    "datasource": {
      "id": "GetSupportRequests",
      "isAutoGenerated": false,
      "name": "GetSupportRequests",
      "pluginId": "restapi-plugin"
    },
    "executeOnLoad": false,
    "name": "Api2",
    "pageId": "Quản lý đơn yêu cầu cứu trợ",
    "userSetOnLoad": false
  }
}