{
  "gitSyncId": "673f672562b6fd1870633c84_9d43b211-ffb6-4dfc-a788-9d4e81d70348",
  "id": "Trang chủ_JSObject1.myFun1",
  "pluginId": "js-plugin",
  "pluginType": "JS",
  "unpublishedAction": {
    "actionConfiguration": {
      "encodeParamsToggle": true,
      "jsArguments": [],
      "paginationType": "NONE",
      "timeoutInMillisecond": 10000
    },
    "clientSideExecution": true,
    "collectionId": "Trang chủ_JSObject1",
    "confirmBeforeExecute": false,
    "datasource": {
      "isAutoGenerated": false,
      "name": "UNUSED_DATASOURCE",
      "pluginId": "js-plugin"
    },
    "dynamicBindingPathList": [
      {
        "key": "body"
      }
    ],
    "executeOnLoad": false,
    "fullyQualifiedName": "JSObject1.myFun1",
    "name": "myFun1",
    "pageId": "Trang chủ",
    "userSetOnLoad": false
  }
}